macdaily/__init__.py
macdaily/__main__.py
macdaily/api/archive.py
macdaily/api/bundle.py
macdaily/api/cleanup.py
macdaily/api/config.py
macdaily/api/dependency.py
macdaily/api/help.py
macdaily/api/install.py
macdaily/api/launch.py
macdaily/api/logging.py
macdaily/api/postinstall.py
macdaily/api/reinstall.py
macdaily/api/uninstall.py
macdaily/api/update.py
macdaily/cli/archive.py
macdaily/cli/bundle.py
macdaily/cli/cleanup.py
macdaily/cli/config.py
macdaily/cli/dependency.py
macdaily/cli/help.py
macdaily/cli/install.py
macdaily/cli/launch.py
macdaily/cli/logging.py
macdaily/cli/postinstall.py
macdaily/cli/reinstall.py
macdaily/cli/uninstall.py
macdaily/cli/update.py
macdaily/cls/command.py
macdaily/cls/bundle/dump.py
macdaily/cls/bundle/load.py
macdaily/cls/cleanup/brew.py
macdaily/cls/cleanup/cask.py
macdaily/cls/cleanup/npm.py
macdaily/cls/cleanup/pip.py
macdaily/cls/dependency/brew.py
macdaily/cls/dependency/pip.py
macdaily/cls/install/apm.py
macdaily/cls/install/brew.py
macdaily/cls/install/cask.py
macdaily/cls/install/gem.py
macdaily/cls/install/mas.py
macdaily/cls/install/npm.py
macdaily/cls/install/pip.py
macdaily/cls/install/system.py
macdaily/cls/logging/apm.py
macdaily/cls/logging/app.py
macdaily/cls/logging/brew.py
macdaily/cls/logging/cask.py
macdaily/cls/logging/gem.py
macdaily/cls/logging/mas.py
macdaily/cls/logging/npm.py
macdaily/cls/logging/pip.py
macdaily/cls/logging/tap.py
macdaily/cls/reinstall/brew.py
macdaily/cls/reinstall/cask.py
macdaily/cls/uninstall/brew.py
macdaily/cls/uninstall/cask.py
macdaily/cls/uninstall/pip.py
macdaily/cls/update/apm.py
macdaily/cls/update/brew.py
macdaily/cls/update/cask.py
macdaily/cls/update/gem.py
macdaily/cls/update/mas.py
macdaily/cls/update/npm.py
macdaily/cls/update/pip.py
macdaily/cls/update/system.py
macdaily/cmd/archive.py
macdaily/cmd/bundle.py
macdaily/cmd/cleanup.py
macdaily/cmd/config.py
macdaily/cmd/dependency.py
macdaily/cmd/install.py
macdaily/cmd/launch.py
macdaily/cmd/logging.py
macdaily-2019.8.4.dist-info/LICENSE
macdaily-2019.8.4.dist-info/METADATA
macdaily-2019.8.4.dist-info/WHEEL
macdaily-2019.8.4.dist-info/entry_points.txt
macdaily-2019.8.4.dist-info/top_level.txt
macdaily-2019.8.4.dist-info/RECORD
