Metadata-Version: 2.1
Name: macdaily
Version: 2019.8.4
Summary: macOS Automated Package Manager
Home-page: https://github.com/JarryShaw/MacDaily#macdaily
Author: Jarry Shaw
Author-email: jarryshaw@icloud.com
License: Apple Public Source License
Keywords: daily utility script
Platform: UNKNOWN
Classifier: Development Status :: 4 - Beta
Classifier: Environment :: Console
Classifier: Environment :: MacOS X
Classifier: Intended Audience :: Developers
Classifier: License :: OSI Approved :: Apple Public Source License
Classifier: Natural Language :: English
Classifier: Operating System :: MacOS
Classifier: Operating System :: MacOS :: MacOS X
Classifier: Programming Language :: Python
Classifier: Programming Language :: Python :: 3
Classifier: Programming Language :: Python :: 3.4
Classifier: Programming Language :: Python :: 3.5
Classifier: Programming Language :: Python :: 3.6
Classifier: Programming Language :: Python :: 3.7
Classifier: Programming Language :: Python :: 3.8
Classifier: Programming Language :: Python :: 3 :: Only
Classifier: Programming Language :: Python :: Implementation :: CPython
Classifier: Programming Language :: Python :: Implementation :: PyPy
Classifier: Topic :: Utilities
Requires-Python: >=3.4
Provides-Extra: config
Provides-Extra: tree
Provides-Extra: ptyng
Provides-Extra: all
